{
  "name": "開発品質ガイドライン",
  "theme": "#FF5168",
  "favicon": "/assets/favicon.ico",
  "logo": "https://mycdn.com/awesome-logo.png",
  "logoDark": "/assets/logo-dark.png",
  "docsearch": {
    "appId": "...",
    "apiKey": "...",
    "indexName": "..."
  },
  "anchors": [
    {
      "title": "ホームページ",
      "icon": "house",
      "link": "https://pentagon.tokyo/"
    },
    {
      "title": "技術ブログ",
      "icon": "terminal",
      "link": "https://blog.pentagon.tokyo/"
    },
    {
      "title": "求人・採用情報",
      "icon": "briefcase",
      "link": "https://job.pentagon.tokyo/"
    },
    {
      "title": "YouTube",
      "icon": "play",
      "link": "https://www.youtube.com/@pentagon-tokyo/videos"
    }
  ],
  "sidebar": [
    ["まずはじめに", "/"],
    [
      "報連相",
      [
        ["Reference API", "/reference"],
        ["FAQs", "/faqs"]
      ]
    ],
    [
      "チケット作成",
      [
        ["仕様／指摘内容の理解", "/reference"],
        ["チケット仕様確認", "/reference"],
        ["マイルストーン設定", "/reference"],
        ["アサイン", "/reference"],
        ["スケジュール設定", "/reference"]
      ]
    ],
    [
      "チケット仕様確認",
      [
        ["予定工数入力", "/reference"],
        ["ガントチャート確認", "/reference"],
        ["設計／修正箇所の検討", "/reference"]
      ]
    ],
    [
      "実装",
      [
        ["ビルド", "/reference"],
        ["ブランチ作成", "/reference"],
        ["コーディング", "/reference"],
        ["動作確認", "/reference"],
        ["プルリクエスト作成", "/reference"],
        ["レビュー依頼", "/reference"]
      ]
    ],
    [
      "レビュー",
      [
        ["期待値理解", "/reference"],
        ["変更内容確認", "/reference"],
        ["ソースコード確認", "/reference"],
        ["関連箇所のチェック", "/reference"],
        ["動作確認", "/reference"],
        ["修正箇所の指摘", "/reference"],
        ["マージ", "/reference"],
        ["実績工数入力", "/reference"]
      ]
    ],
    [
      "テスト",
      [
        ["端末確認", "/reference"],
        ["テストシート作成", "/reference"],
        ["バグ共有", "/reference"],
        ["チケット作成", "/reference"],
        ["チケットクローズ", "/reference"]
      ]
    ]
  ]
}
